fun/__init__.py
fun/fun.py
fun/main.py
fun/tasks.py
wfun-1.0.0.dist-info/METADATA
wfun-1.0.0.dist-info/WHEEL
wfun-1.0.0.dist-info/entry_points.txt
wfun-1.0.0.dist-info/top_level.txt
wfun-1.0.0.dist-info/RECORD
