Metadata-Version: 2.1
Name: wfun
Version: 1.0.0
Summary: UNKNOWN
Home-page: UNKNOWN
Author: UNKNOWN
Author-email: UNKNOWN
License: UNKNOWN
Platform: UNKNOWN
Requires-Dist: invoke
Requires-Dist: requests
Requires-Dist: PyLyrics
Requires-Dist: soco
